pss1830ssh/__init__.py
pss1830ssh/pss1830.py
pss1830ssh/pss1830cli.py
pss1830ssh/pss1830root.py
nokia1830pss-1.0.3.dist-info/LICENSE
nokia1830pss-1.0.3.dist-info/METADATA
nokia1830pss-1.0.3.dist-info/WHEEL
nokia1830pss-1.0.3.dist-info/top_level.txt
nokia1830pss-1.0.3.dist-info/RECORD
