Metadata-Version: 2.1
Name: nokia1830pss
Version: 1.0.3
Summary: A SSH library for Nokia 1830-PSS NEs
Home-page: https://github.com/trungdtbk/nokia-1830pss-ssh.git
Author: Trung Truong
Author-email: trungdtbk@gmail.com
License: UNKNOWN
Platform: UNKNOWN
Classifier: Programming Language :: Python :: 2.7
Classifier: Programming Language :: Python :: 3
Classifier: Development Status :: 4 - Beta
Classifier: Environment :: Plugins
Classifier: Intended Audience :: Developers
Classifier: License :: OSI Approved :: MIT License
Classifier: Topic :: System :: Networking
Requires-Dist: paramiko (==2.7.0)
